kucoin/__init__.py
kucoin/async_client.py
kucoin/async_client_base.py
kucoin/base_client.py
kucoin/client.py
kucoin/exceptions.py
kucoin/utils.py
kucoin/asyncio/__init__.py
kucoin/asyncio/websockets.py
python_kucoin-2.2.0.dist-info/LICENSE
python_kucoin-2.2.0.dist-info/METADATA
python_kucoin-2.2.0.dist-info/WHEEL
python_kucoin-2.2.0.dist-info/top_level.txt
python_kucoin-2.2.0.dist-info/RECORD
